odoo/addons/shopinvader_api_payment_cart/README.rst
odoo/addons/shopinvader_api_payment_cart/__init__.py
odoo/addons/shopinvader_api_payment_cart/__manifest__.py
odoo/addons/shopinvader_api_payment_cart/i18n/shopinvader_api_payment_cart.pot
odoo/addons/shopinvader_api_payment_cart/readme/CONTRIBUTORS.rst
odoo/addons/shopinvader_api_payment_cart/readme/DESCRIPTION.rst
odoo/addons/shopinvader_api_payment_cart/readme/USAGE.rst
odoo/addons/shopinvader_api_payment_cart/routers/__init__.py
odoo/addons/shopinvader_api_payment_cart/routers/cart.py
odoo/addons/shopinvader_api_payment_cart/routers/payment.py
odoo/addons/shopinvader_api_payment_cart/schemas/__init__.py
odoo/addons/shopinvader_api_payment_cart/static/description/index.html
odoo/addons/shopinvader_api_payment_cart/tests/__init__.py
odoo/addons/shopinvader_api_payment_cart/tests/test_pay_cart.py
odoo/addons/shopinvader_api_payment_cart/tests/test_payment_cart_info.py
odoo_addon_shopinvader_api_payment_cart-16.0.1.1.0.dist-info/METADATA
odoo_addon_shopinvader_api_payment_cart-16.0.1.1.0.dist-info/WHEEL
odoo_addon_shopinvader_api_payment_cart-16.0.1.1.0.dist-info/top_level.txt
odoo_addon_shopinvader_api_payment_cart-16.0.1.1.0.dist-info/RECORD
